frolick/__init__.py
frolick-0.0.1.dist-info/LICENSE
frolick-0.0.1.dist-info/METADATA
frolick-0.0.1.dist-info/WHEEL
frolick-0.0.1.dist-info/top_level.txt
frolick-0.0.1.dist-info/RECORD
